stix_shifter_modules/async_template/__init__.py
stix_shifter_modules/async_template/entry_point.py
stix_shifter_modules/async_template/transformers.py
stix_shifter_modules/async_template/configuration/config.json
stix_shifter_modules/async_template/configuration/dialects.json
stix_shifter_modules/async_template/configuration/lang_en.json
stix_shifter_modules/async_template/stix_translation/__init__.py
stix_shifter_modules/async_template/stix_translation/json_to_stix_translator.py
stix_shifter_modules/async_template/stix_translation/query_constructor.py
stix_shifter_modules/async_template/stix_translation/query_translator.py
stix_shifter_modules/async_template/stix_translation/results_translator.py
stix_shifter_modules/async_template/stix_translation/transformers.py
stix_shifter_modules/async_template/stix_translation/json/dialect1_from_stix_map.json
stix_shifter_modules/async_template/stix_translation/json/dialect2_from_stix_map.json
stix_shifter_modules/async_template/stix_translation/json/operators.json
stix_shifter_modules/async_template/stix_translation/json/to_stix_map.json
stix_shifter_modules/async_template/stix_transmission/__init__.py
stix_shifter_modules/async_template/stix_transmission/api_client.py
stix_shifter_modules/async_template/stix_transmission/delete_connector.py
stix_shifter_modules/async_template/stix_transmission/error_mapper.py
stix_shifter_modules/async_template/stix_transmission/ping_connector.py
stix_shifter_modules/async_template/stix_transmission/query_connector.py
stix_shifter_modules/async_template/stix_transmission/results_connector.py
stix_shifter_modules/async_template/stix_transmission/status_connector.py
stix_shifter_modules_async_template-8.0.2.dist-info/licenses/AUTHORS.md
stix_shifter_modules_async_template-8.0.2.dist-info/licenses/LICENSE.md
stix_shifter_modules_async_template-8.0.2.dist-info/licenses/NOTICE
stix_shifter_modules_async_template-8.0.2.dist-info/METADATA
stix_shifter_modules_async_template-8.0.2.dist-info/WHEEL
stix_shifter_modules_async_template-8.0.2.dist-info/top_level.txt
stix_shifter_modules_async_template-8.0.2.dist-info/RECORD
